{
"type": "FeatureCollection",
"name": "Badge 7760",
"crs": { "type": "name", "properties": { "name": "urn:ogc:def:crs:OGC:1.3:CRS84" } },
"features": [
{ "type": "Feature", "properties": { "Name": "#7760", "description": "<div dir='rtl' style='font-family:Arial;'><b>שם:</b> ניצן שגב<br/><b>תאריך:</b> 23-11-2025<br/><b>ID:</b> 2847<br/><b>FB:</b> <a href='https://www.facebook.com/groups/beshvil.yael/posts/3817304881895968'>https://www.facebook.com/groups/beshvil.yael/posts/3817304881895968</a><br/><br/><img src='https://drive.google.com/uc?export=view&amp;id=17ALQx6xmnwujd9OwW2RTqjKwDRnvRLAw' width='450'/><br/></div>", "tessellate": -1, "extrude": 0, "visibility": -1 }, "geometry": { "type": "Point", "coordinates": [ 35.10439, 33.09293, 0.0 ] } },
{ "type": "Feature", "properties": { "Name": "#7761", "description": "<div dir='rtl' style='font-family:Arial;'><b>שם:</b> <br/><b>תאריך:</b> 23-11-2025<br/><b>ID:</b> 2847<br/><b>FB:</b> <a href='https://www.facebook.com/groups/beshvil.yael/posts/3817304881895968'>https://www.facebook.com/groups/beshvil.yael/posts/3817304881895968</a><br/><br/><img src='https://drive.google.com/uc?export=view&amp;id=17ALQx6xmnwujd9OwW2RTqjKwDRnvRLAw' width='450'/><br/></div>", "tessellate": -1, "extrude": 0, "visibility": -1 }, "geometry": { "type": "Point", "coordinates": [ 35.10439, 33.0932, 0.0 ] } },
{ "type": "Feature", "properties": { "Name": "#7760", "description": "<div dir='rtl' style='font-family:Arial;'><b>שם:</b> ניצן שגב<br/><b>תאריך:</b> 29-11-2025<br/><b>ID:</b> 2905<br/><b>FB:</b> <a href='https://www.facebook.com/groups/beshvil.yael/posts/3822459724713817/'>https://www.facebook.com/groups/beshvil.yael/posts/3822459724713817/</a><br/><br/><img src='https://drive.google.com/uc?export=view&amp;id=1ucnhflrhupBNtOoCijcGE2W1LWSfZb6H' width='450'/><br/></div>", "tessellate": -1, "extrude": 0, "visibility": -1 }, "geometry": { "type": "Point", "coordinates": [ 34.89649, 32.51127, 0.0 ] } },
{ "type": "Feature", "properties": { "Name": "#7760", "description": "<div dir='rtl' style='font-family:Arial;'><b>שם:</b> ניצן שגב<br/><b>תאריך:</b> 26-12-2025<br/><b>ID:</b> 3177<br/><b>FB:</b> <a href='https://www.facebook.com/groups/beshvil.yael/posts/3845482172411572'>https://www.facebook.com/groups/beshvil.yael/posts/3845482172411572</a><br/><br/><img src='https://drive.google.com/uc?export=view&amp;id=1H6SsiBSDnnAHU8WIC-YYX2qbliIzZOIG' width='450'/><br/></div>", "tessellate": -1, "extrude": 0, "visibility": -1 }, "geometry": { "type": "Point", "coordinates": [ 35.39169, 32.91366, 0.0 ] } },
{ "type": "Feature", "properties": { "Name": "#7760", "description": "<div dir='rtl' style='font-family:Arial;'><b>שם:</b> ניצן שגב<br/><b>תאריך:</b> 14-02-2026<br/><b>ID:</b> 3716<br/><b>FB:</b> <a href='https://www.facebook.com/groups/beshvil.yael/posts/3890326007927188/'>https://www.facebook.com/groups/beshvil.yael/posts/3890326007927188/</a><br/><br/><img src='https://drive.google.com/uc?export=view&amp;id=1hzzqW5MXp3jX6HIavJWe890f3gTIcnWC' width='450'/><br/></div>", "tessellate": -1, "extrude": 0, "visibility": -1 }, "geometry": { "type": "Point", "coordinates": [ 35.03044, 31.78656, 0.0 ] } }
]
}
